{"cameraMode":{"drawMode":0,"name":"Shaded","section":"Shading Mode"},"sceneLighting":false,"audioPlay":false,"sceneViewState":{"m_AlwaysRefresh":false,"showFog":true,"showSkybox":false,"showFlares":true,"showImageEffects":true,"showParticleSystems":true,"showVisualEffectGraphs":true,"m_FxEnabled":true},"in2DMode":false,"pivot":{"x":-408.771484375,"y":2.3232460021972658,"z":7.19472599029541},"rotation":{"x":-0.00574978394433856,"y":0.9940363764762878,"z":-0.0681125670671463,"w":-0.08675074577331543},"size":1.3871216773986817,"orthographic":false}